lg_payroll_api/__init__.py
lg_payroll_api/helpers/__init__.py
lg_payroll_api/helpers/api_results.py
lg_payroll_api/helpers/authentication.py
lg_payroll_api/helpers/base_client.py
lg_payroll_api/helpers/envelope_logger.py
lg_payroll_api/scripts/__init__.py
lg_payroll_api/scripts/additional_information.py
lg_payroll_api/scripts/additional_information_value.py
lg_payroll_api/scripts/company.py
lg_payroll_api/scripts/cost_center.py
lg_payroll_api/scripts/employee.py
lg_payroll_api/scripts/employment_contract.py
lg_payroll_api/scripts/movement.py
lg_payroll_api/scripts/office_local.py
lg_payroll_api/scripts/organizational_unit.py
lg_payroll_api/scripts/position.py
lg_payroll_api/scripts/reports.py
lg_payroll_api/scripts/role.py
lg_payroll_api/scripts/work_scale.py
lg_payroll_api/utils/__init__.py
lg_payroll_api/utils/aux_functions.py
lg_payroll_api/utils/enums.py
lg_payroll_api/utils/lg_exceptions.py
lg_payroll_api/utils/models.py
lg_payroll_api/utils/report_parameters.py
lg_payroll_api/utils/settings.py
lg_payroll_api-0.1.19.dist-info/METADATA
lg_payroll_api-0.1.19.dist-info/WHEEL
lg_payroll_api-0.1.19.dist-info/licenses/LICENSE
lg_payroll_api-0.1.19.dist-info/RECORD
